Metadata-Version: 1.0
Name: melopero-bme280
Version: 0.1.0
Summary: A module to easily access melopero's bme280 features.
Home-page: https://github.com/melopero/Melopero_BME280
Author: Leonardo La Rocca
Author-email: info@melopero.com
License: MIT
Platform: UNKNOWN
